docgen/__init__.py
docgen/cli.py
docgen/converter.py
docgen/finder.py
docgen/loader.py
docgen/patcher.py
docgen/rest.py
docgen/utils.py
robotframework_docgen-0.17.0.dist-info/entry_points.txt
robotframework_docgen-0.17.0.dist-info/METADATA
robotframework_docgen-0.17.0.dist-info/WHEEL
robotframework_docgen-0.17.0.dist-info/RECORD
