Metadata-Version: 2.1
Name: robotframework-docgen
Version: 0.17.0
Summary: Robot Framework documentation finder and generator
Home-page: https://github.com/robocorp/robotframework-docgen
License: Apache-2.0
Author: RPA Framework
Author-email: rpafw@robocorp.com
Requires-Python: >=3.8,<4.0
Classifier: License :: OSI Approved :: Apache Software License
Classifier: Programming Language :: Python :: 3
Classifier: Programming Language :: Python :: 3.8
Classifier: Programming Language :: Python :: 3.9
Classifier: Programming Language :: Python :: 3.10
Classifier: Programming Language :: Python :: 3.11
Classifier: Programming Language :: Python :: 3.12
Requires-Dist: robotframework (>=3.2.2,!=4.0.1,!=6.1.0,<8.0.0)
Project-URL: Documentation, https://github.com/robocorp/robotframework-docgen
Project-URL: Repository, https://github.com/robocorp/robotframework-docgen
